README.md
setup.py
Rigol1000z/__init__.py
Rigol1000z/commands.py
Rigol1000z/constants.py
Rigol1000z/rigol1000z.py
Rigol1000z/rigol1000zcommandmenu.py
Rigol1000z_remote.egg-info/PKG-INFO
Rigol1000z_remote.egg-info/SOURCES.txt
Rigol1000z_remote.egg-info/dependency_links.txt
Rigol1000z_remote.egg-info/requires.txt
Rigol1000z_remote.egg-info/top_level.txt