Metadata-Version: 2.1
Name: Rigol1000z-remote
Version: 0.3.1
Summary: Python VISA (USB and Ethernet) library for interface with Rigol DS1000z series oscilloscopes.
Home-page: https://github.com/AlexZettler/Rigol1000z
Author: Alexander Zettler(@AlexZettler), @jeanyvesb9, @jtambasco
Author-email: azettler@live.com
License: UNKNOWN
Platform: UNKNOWN
Classifier: Programming Language :: Python :: 3.7
Classifier: Topic :: Software Development :: Libraries :: Python Modules
Classifier: Topic :: System :: Hardware :: Hardware Drivers
